{"dkQlQ5r08zdHXYfpO1OoWg==":"mbr-1620x1080.png","I51+IgKEm9MfPyDSAJUsXg==":"logo-blog-834x200.png","4dTs0EtcxU349SzQRWo2Tw==":"callpage_logo_white_transparent-875x183.png","DEk5w4W7LehbMBoX3+m4zg==":"callpage_logo_white_transparent-800x166.png","B6b7qlEL5DnnR0q8D/f8EQ==":"logo-callpage-500%20copy-1000x238.png","yBTzUssNVO8xZa92syjqNw==":"callpage_logo_white_transparent-400x84.png","FyvqqrB55kEJmAvdTVQE2A==":"callpage_logo_white_transparent-247x52.png","8jC+NlaAmPYafAr7uccL1w==":"callpage-logo-white-300x250.png","vg/LftQWMtlYEpyuUthcWQ==":"callpage-logo-white-500x400.png","zmmH9YH5B0XRLTWfFCq+Aw==":"callpage-logo-black-409x99.png","sLr6xfAGpq+KaTH24FcDAQ==":"callpage-logo-black-600x150.png","kwI21poWg2LbKI0Cab04Ew==":"audi-logo-700x394.png","l8gvecXFy3nSt3vHDjfvZw==":"logo_orange_z_polem_rgb-181x182.png","tWBdNFBePvtEPsi+1iFzbg==":"medicoverlogo-250x150.png","SSPKstu/q3uZSPNeHzah6w==":"raiffeisenpolbank-callpage-250x92.png","xCz3h8JAW8dt+cvsBE6YAQ==":"toyota_logo_newes-144x120.png","nBkVy5OnzjqxJy+sXP2GPQ==":"pwc_fl_c-250x211.png","rfDI5E9lPAwz3ro2CQI6lg==":"viessmann-logo.svg-250x54.png","VNQq5HzKuOhkimNKph1EXA==":"vw-112x72.png","3MjnYHIyUoc36SB3rAU/Ow==":"logo_orange_z_polem_rgb-250x250.png","sFEZLodX3DlaRBIMyCmzOA==":"orange-222x222.png","+tzAPZcmoqxM4SfgBOfIlg==":"audi-700x400.png","29sbz/OyMidLtrhEtDxRRA==":"medicover-700x400.png","S4ndEZrf3tg9Ov1wREXyYQ==":"orange-700x400.png","D5EBCo/E1Gj/8ER4CbBN6w==":"raiffeisen-700x400.png","VPRtP1thnCKgehqa6iIbMw==":"toyota-700x400.png","EUYe22cazCuXzNqQrYgXUg==":"viesmann-700x400.png","MxjK6b71cQr1rhVQRNv4kQ==":"_volkswagen-700x400.png"}